schema_matching/__init__.py
schema_matching/cal_column_similarity.py
schema_matching/init.py
schema_matching/relation_features.py
schema_matching/self_features.py
schema_matching/train.py
schema_matching/utils.py
schema_matching/model/2022-04-12-12-06-32/0.model
schema_matching/model/2022-04-12-12-06-32/0.threshold
schema_matching/model/2022-04-12-12-06-32/1.model
schema_matching/model/2022-04-12-12-06-32/1.threshold
schema_matching/model/2022-04-12-12-06-32/10.model
schema_matching/model/2022-04-12-12-06-32/10.threshold
schema_matching/model/2022-04-12-12-06-32/11.model
schema_matching/model/2022-04-12-12-06-32/11.threshold
schema_matching/model/2022-04-12-12-06-32/12.model
schema_matching/model/2022-04-12-12-06-32/12.threshold
schema_matching/model/2022-04-12-12-06-32/13.model
schema_matching/model/2022-04-12-12-06-32/13.threshold
schema_matching/model/2022-04-12-12-06-32/14.model
schema_matching/model/2022-04-12-12-06-32/14.threshold
schema_matching/model/2022-04-12-12-06-32/15.model
schema_matching/model/2022-04-12-12-06-32/15.threshold
schema_matching/model/2022-04-12-12-06-32/2.model
schema_matching/model/2022-04-12-12-06-32/2.threshold
schema_matching/model/2022-04-12-12-06-32/3.model
schema_matching/model/2022-04-12-12-06-32/3.threshold
schema_matching/model/2022-04-12-12-06-32/4.model
schema_matching/model/2022-04-12-12-06-32/4.threshold
schema_matching/model/2022-04-12-12-06-32/5.model
schema_matching/model/2022-04-12-12-06-32/5.threshold
schema_matching/model/2022-04-12-12-06-32/6.model
schema_matching/model/2022-04-12-12-06-32/6.threshold
schema_matching/model/2022-04-12-12-06-32/7.model
schema_matching/model/2022-04-12-12-06-32/7.threshold
schema_matching/model/2022-04-12-12-06-32/8.model
schema_matching/model/2022-04-12-12-06-32/8.threshold
schema_matching/model/2022-04-12-12-06-32/9.model
schema_matching/model/2022-04-12-12-06-32/9.threshold
schema_matching-1.0.4.dist-info/LICENSE
schema_matching-1.0.4.dist-info/METADATA
schema_matching-1.0.4.dist-info/WHEEL
schema_matching-1.0.4.dist-info/top_level.txt
schema_matching-1.0.4.dist-info/RECORD
