Metadata-Version: 2.1
Name: schema-matching
Version: 1.0.4
Summary: Using XGboost and Sentence-Transformers to perform schema matching task on tables.
Home-page: https://github.com/fireindark707/Python-Schema-Matching
Author: fireindark707
Author-email: phoenix000.taipei@gmail.com
Maintainer: fireindark707
Maintainer-email: phoenix000.taipei@gmail.com
License: UNKNOWN
Download-URL: https://github.com/fireindark707/Python-Schema-Matching/archive/refs/tags/v0.2.tar.gz
Keywords: schema matching,dataset discovery,schema mapping,XGboost,sentence-transformers,NLP
Platform: UNKNOWN
Requires-Python: >=3.6,<3.11
License-File: LICENSE
Requires-Dist: numpy (>=1.19.5)
Requires-Dist: pandas (>=1.1.5)
Requires-Dist: nltk (>=3.6.5)
Requires-Dist: python-dateutil (>=2.8.2)
Requires-Dist: sentence-transformers (>=2.1.0)
Requires-Dist: xgboost (>=1.5.2)
Requires-Dist: strsimpy (>=0.2.1)
